inko/__init__.py
inko_py-1.0.0.dist-info/LICENSE
inko_py-1.0.0.dist-info/METADATA
inko_py-1.0.0.dist-info/WHEEL
inko_py-1.0.0.dist-info/top_level.txt
inko_py-1.0.0.dist-info/RECORD
