Metadata-Version: 2.1
Name: inko-py
Version: 1.0.0
Summary: Python pip module of Inko.js
Home-page: https://github.com/JackCme/inko.py
Author: JackCme
Author-email: pitou_106@naver.com
License: UNKNOWN
Platform: UNKNOWN
Classifier: Programming Language :: Python :: 3
Classifier: License :: OSI Approved :: MIT License
Classifier: Operating System :: OS Independent
Requires-Python: >=3.6
